live_differ/__init__.py
live_differ/__main__.py
live_differ/cli.py
live_differ/core.py
live_differ/assets/images/screenshot.png
live_differ/modules/__init__.py
live_differ/modules/differ.py
live_differ/modules/watcher.py
live_differ/static/css/styles.css
live_differ/static/js/main.js
live_differ/templates/error.html
live_differ/templates/index.html
live_differ/templates/index_footer.html
live_differ/templates/index_header.html
live_differ-1.0.3.dist-info/LICENSE
live_differ-1.0.3.dist-info/METADATA
live_differ-1.0.3.dist-info/WHEEL
live_differ-1.0.3.dist-info/entry_points.txt
live_differ-1.0.3.dist-info/top_level.txt
live_differ-1.0.3.dist-info/RECORD
