Metadata-Version: 2.1
Name: live-differ
Version: 1.0.3
Summary: A real-time file difference viewer with live updates
Author: manthanby
License:                     GNU GENERAL PUBLIC LICENSE
Project-URL: Homepage, https://github.com/manthanby/live_differ
Project-URL: Repository, https://github.com/manthanby/live_differ.git
Project-URL: Issues, https://github.com/manthanby/live_differ/issues
Classifier: Development Status :: 3 - Alpha
Classifier: Environment :: Console
Classifier: Environment :: Web Environment
Classifier: Framework :: Flask
Classifier: Intended Audience :: Developers
Classifier: License :: OSI Approved :: MIT License
Classifier: Programming Language :: Python :: 3
Classifier: Programming Language :: Python :: 3.7
Classifier: Programming Language :: Python :: 3.8
Classifier: Programming Language :: Python :: 3.9
Classifier: Programming Language :: Python :: 3.10
Classifier: Topic :: Software Development :: Libraries :: Python Modules
Requires-Python: >=3.7
License-File: LICENSE
Requires-Dist: flask>=2.0.0
Requires-Dist: flask-socketio>=5.0.0
Requires-Dist: typer>=0.9.0
Requires-Dist: watchdog>=2.1.0
Requires-Dist: flask-cors>=4.0.0
